<?xml version="1.0" encoding="UTF-8"?>
<mule xmlns:ee="http://www.mulesoft.org/schema/mule/ee/core" xmlns:doc="http://www.mulesoft.org/schema/mule/documentation" xmlns="http://www.mulesoft.org/schema/mule/core" xmlns:apikit="http://www.mulesoft.org/schema/mule/mule-apikit" xmlns:http="http://www.mulesoft.org/schema/mule/http" xmlns:xsi="http://www.w3.org/2001/XMLSchema-instance" xsi:schemaLocation="http://www.mulesoft.org/schema/mule/core http://www.mulesoft.org/schema/mule/core/current/mule.xsd http://www.mulesoft.org/schema/mule/http http://www.mulesoft.org/schema/mule/http/current/mule-http.xsd http://www.mulesoft.org/schema/mule/mule-apikit http://www.mulesoft.org/schema/mule/mule-apikit/current/mule-apikit.xsd 
http://www.mulesoft.org/schema/mule/ee/core http://www.mulesoft.org/schema/mule/ee/core/current/mule-ee.xsd">
    <flow name="retrieveconsolidatedroutesandschedulesxpapi-main">
        <http:listener config-ref="retrieveconsolidatedroutesandschedulesxpapi-httpListenerConfig" path="/api/*">
            <http:response statusCode="#[vars.httpStatus default 200]">
                <http:headers>#[vars.outboundHeaders default {}]</http:headers>
            </http:response>
            <http:error-response statusCode="#[vars.httpStatus default 500]">
                <http:body>#[payload]</http:body>
                <http:headers>#[vars.outboundHeaders default {}]</http:headers>
            </http:error-response>
        </http:listener>
        <apikit:router config-ref="retrieveconsolidatedroutesandschedulesxpapi-config" />
        <error-handler ref="globalErrorHandlerError_Handler">
            
           
        </error-handler>
    </flow>
    <flow name="retrieveconsolidatedroutesandschedulesxpapi-console">
        <http:listener config-ref="retrieveconsolidatedroutesandschedulesxpapi-httpListenerConfig" path="/console/*">
            <http:response statusCode="#[vars.httpStatus default 200]">
                <http:headers>#[vars.outboundHeaders default {}]</http:headers>
            </http:response>
            <http:error-response statusCode="#[vars.httpStatus default 500]">
                <http:body>#[payload]</http:body>
                <http:headers>#[vars.outboundHeaders default {}]</http:headers>
            </http:error-response>
        </http:listener>
        <apikit:console config-ref="retrieveconsolidatedroutesandschedulesxpapi-config" />
		<error-handler ref="globalErrorHandlerError_Handler" />
    </flow>
    <sub-flow name="retrieveconsolidatedroutesandschedulesxpapiSub_Flow" doc:id="a3514f0e-0237-4732-ae97-dc916c942208" >
		<ee:transform doc:name="Initialise Variables for Request Event Transform Message" doc:id="13a6c0d0-4a71-4e66-922f-8309bee87868" >
			<ee:variables>
				<ee:set-variable variableName="transactionId"><![CDATA[%dw 2.0
output application/java
---
attributes.headers.transactionId]]></ee:set-variable>
				<ee:set-variable variableName="departureLocation" ><![CDATA[%dw 2.0
output application/java
---
attributes.queryParams.'departureLocation']]></ee:set-variable>
				<ee:set-variable variableName="destinationLocation" ><![CDATA[%dw 2.0
output application/java
---
attributes.queryParams.'destinationLocation']]></ee:set-variable>
				<ee:set-variable variableName="transportCompany" ><![CDATA[attributes.queryParams.'companyName']]></ee:set-variable>
				<ee:set-variable variableName="transportType" ><![CDATA[attributes.uriParams.'transportType']]></ee:set-variable>
            </ee:variables>
		</ee:transform>
	</sub-flow>
	<flow name="get:\booking\(transportType)\routes:retrieveconsolidatedroutesandschedulesxpapi-config">
        <flow-ref doc:name="Flow Reference" doc:id="1005ac2e-869a-42af-833a-cf8dbc6ffef2" name="retrieveconsolidatedroutesandschedulesxpapiSub_Flow"/>
		<logger level="INFO" doc:name="Logger" doc:id="fb064e9b-7a21-420b-8f8e-a5e16fb5381f" message="Request Recieved for Routes BAPI For TransactionId: #[vars.transactionId]"/>
		<flow-ref doc:name="Flow Reference" doc:id="d4b243fd-5240-47bd-b1c9-bf68fb9b1633" name="getRoutes-implementationSub_Flow"/>
		<logger level="INFO" doc:name="Logger" doc:id="53a1820e-4b9e-48a5-a2ad-dcc0362a7c96" message="Response Sent for Routes BAPI For TransactionId: #[vars.transactionId]"/>
    </flow>
    <flow name="get:\booking\(transportType)\schedules:retrieveconsolidatedroutesandschedulesxpapi-config">
        <flow-ref doc:name="Flow Reference" doc:id="32134645-c887-4950-aeb8-4824525a593c" name="retrieveconsolidatedroutesandschedulesxpapiSub_Flow"/>
		<logger level="INFO" doc:name="Logger" doc:id="08153f5e-cfec-442c-94df-f9e35925898f" message="Request Recieved for Schedules BAPI For TransactionId: #[vars.transactionId]"/>
		<flow-ref doc:name="Flow Reference" doc:id="d41cf9db-21e4-4a96-9998-292911a2b7ff" name="getSchedules-implementationSub_Flow"/>
		<logger level="INFO" doc:name="Logger" doc:id="fedd60c0-7315-43f7-bdeb-edda1fcbb7fb" message="Response Sent for Schedules BAPI For TransactionId: #[vars.transactionId]"/>
    </flow>
</mule>
